batman/__init__.py
batman/driver.py
batman/ui.py
batman/functions/__init__.py
batman/functions/analytical.py
batman/functions/db_generic.py
batman/functions/db_mascaret.py
batman/functions/utils.py
batman/functions/data/__init__.py
batman/functions/data/data.py
batman/functions/data/elnino.dat
batman/functions/data/input_mascaret.npy
batman/functions/data/marthe.dat
batman/functions/data/output_mascaret.npy
batman/functions/data/tahiti.dat
batman/functions/data/x_sampling.npy
batman/functions/data/y_sampling.npy
batman/functions/telemac_mascaret/__init__.py
batman/functions/telemac_mascaret/db_mascaret.py
batman/functions/telemac_mascaret/run_mascaret/__init__.py
batman/functions/telemac_mascaret/run_mascaret/mascaret_api.py
batman/functions/telemac_mascaret/run_mascaret/print_and_plot.py
batman/input_output/__init__.py
batman/input_output/_tecplot.so
batman/input_output/antares_wrapper.py
batman/input_output/antares_wrappers.py
batman/input_output/base.py
batman/input_output/dataset.py
batman/input_output/formater.py
batman/input_output/npz.py
batman/input_output/tecplot.py
batman/misc/__init__.py
batman/misc/logging.json
batman/misc/misc.py
batman/misc/nested_pool.py
batman/misc/schema.json
batman/pod/__init__.py
batman/pod/pod.py
batman/space/__init__.py
batman/space/gp_1d_sampler.py
batman/space/gp_sampler.py
batman/space/point.py
batman/space/refiner.py
batman/space/sample.py
batman/space/sampling.py
batman/space/space.py
batman/surrogate/RBFnet.py
batman/surrogate/TreeCut.py
batman/surrogate/__init__.py
batman/surrogate/kriging.py
batman/surrogate/mixture.py
batman/surrogate/multifidelity.py
batman/surrogate/polynomial_chaos.py
batman/surrogate/sk_interface.py
batman/surrogate/surrogate_model.py
batman/tasks/__init__.py
batman/tasks/local_executor.py
batman/tasks/provider_file.py
batman/tasks/provider_function.py
batman/tasks/provider_job.py
batman/tasks/provider_plugin.py
batman/tasks/remote_executor.py
batman/tasks/sample_cache.py
batman/tasks/snapshot.py
ot_batman-1.9.1.dist-info/AUTHORS.rst
ot_batman-1.9.1.dist-info/LICENSE
ot_batman-1.9.1.dist-info/METADATA
ot_batman-1.9.1.dist-info/WHEEL
ot_batman-1.9.1.dist-info/entry_points.txt
ot_batman-1.9.1.dist-info/top_level.txt
ot_batman-1.9.1.dist-info/RECORD
