Metadata-Version: 2.1
Name: ot-batman
Version: 1.9.1
Summary: BATMAN: Statistical analysis for expensive computer codes made easy
Home-page: https://gitlab.com/cerfacs/batman
Maintainer: Pamphile ROY
Maintainer-email: roy@cerfacs.fr
License: CECILL-B
Keywords: surrogate model,uncertainty quantification,statistical analysis,design of experiments,uncertainty visualization
Platform: UNKNOWN
Classifier: Development Status :: 5 - Production/Stable
Classifier: Environment :: Console
Classifier: License :: OSI Approved
Classifier: Intended Audience :: Science/Research
Classifier: Intended Audience :: Developers
Classifier: Natural Language :: English
Classifier: Operating System :: Unix
Classifier: Programming Language :: Python :: 2
Classifier: Programming Language :: Python :: 2.7
Classifier: Programming Language :: Python :: 3
Classifier: Programming Language :: Python :: 3.4
Classifier: Programming Language :: Python :: 3.5
Classifier: Programming Language :: Python :: 3.6
Classifier: Programming Language :: Python :: 3.7
Classifier: Topic :: Documentation :: Sphinx
Classifier: Topic :: Software Development
Classifier: Topic :: Scientific/Engineering
Requires-Python: >=2.7,!=3.0.*,!=3.1.*,!=3.2.*,!=3.3.*
Requires-Dist: scipy (>=0.15)
Requires-Dist: numpy (>=1.13)
Requires-Dist: openturns
Requires-Dist: pandas (>=0.22.0)
Requires-Dist: paramiko (>=2)
Requires-Dist: jsonschema
Requires-Dist: pathos (>=0.2)
Requires-Dist: matplotlib (>=2.1)
Requires-Dist: scikit-learn (>=0.18)
Provides-Extra: doc
Requires-Dist: sphinx-rtd-theme ; extra == 'doc'
Requires-Dist: sphinx (>=1.4) ; extra == 'doc'
Provides-Extra: movie
Requires-Dist: ffmpeg ; extra == 'movie'
